empusa/__init__.py
empusa/tests.py
empusa-0.0.3.dist-info/entry_points.txt
empusa-0.0.3.dist-info/LICENSE
empusa-0.0.3.dist-info/WHEEL
empusa-0.0.3.dist-info/METADATA
empusa-0.0.3.dist-info/RECORD
