Metadata-Version: 2.1
Name: empusa
Version: 0.0.3
Summary: Service discovery tool
Home-page: https://pypi.org/project/empusa
License: BSD-3-Clause
Author: Milos Prchlik
Author-email: mprchlik@redhat.com
Requires-Python: >=3.6,<4.0
Classifier: License :: OSI Approved :: BSD License
Classifier: Operating System :: POSIX :: Linux
Classifier: Programming Language :: Python :: 3
Classifier: Programming Language :: Python :: 3.6
Classifier: Programming Language :: Python :: 3.7
Classifier: Programming Language :: Python :: 3.8
Classifier: Programming Language :: Python :: Implementation :: CPython
Classifier: Topic :: Utilities
Requires-Dist: click
Requires-Dist: python-etcd (>=0.4.5,<0.5.0)
Requires-Dist: tabulate
Project-URL: Repository, https://gitlab.com/testing-farm/empusa
